{
  "id": "9e7ddfbc-6249-45fa-a3be-f7a73ad70ae6",
  "prevId": "00000000-0000-0000-0000-000000000000",
  "version": "7",
  "dialect": "postgresql",
  "tables": {
    "public.admission_meta": {
      "name": "admission_meta",
      "schema": "",
      "columns": {
        "id": {
          "name": "id",
          "type": "uuid",
          "primaryKey": true,
          "notNull": true,
          "default": "gen_random_uuid()"
        },
        "inquiry_id": {
          "name": "inquiry_id",
          "type": "uuid",
          "primaryKey": false,
          "notNull": true
        },
        "academic_year": {
          "name": "academic_year",
          "type": "text",
          "primaryKey": false,
          "notNull": true
        },
        "admission_type": {
          "name": "admission_type",
          "type": "admission_type",
          "typeSchema": "public",
          "primaryKey": false,
          "notNull": true,
          "default": "'NEW'"
        },
        "previously_applied_year": {
          "name": "previously_applied_year",
          "type": "text",
          "primaryKey": false,
          "notNull": false
        },
        "entry_number": {
          "name": "entry_number",
          "type": "text",
          "primaryKey": false,
          "notNull": true
        },
        "admission_number": {
          "name": "admission_number",
          "type": "text",
          "primaryKey": false,
          "notNull": false
        },
        "scholar_number": {
          "name": "scholar_number",
          "type": "text",
          "primaryKey": false,
          "notNull": false
        },
        "created_at": {
          "name": "created_at",
          "type": "timestamp",
          "primaryKey": false,
          "notNull": true,
          "default": "now()"
        },
        "updated_at": {
          "name": "updated_at",
          "type": "timestamp",
          "primaryKey": false,
          "notNull": true,
          "default": "now()"
        }
      },
      "indexes": {},
      "foreignKeys": {
        "admission_meta_inquiry_id_inquiries_id_fk": {
          "name": "admission_meta_inquiry_id_inquiries_id_fk",
          "tableFrom": "admission_meta",
          "tableTo": "inquiries",
          "columnsFrom": [
            "inquiry_id"
          ],
          "columnsTo": [
            "id"
          ],
          "onDelete": "cascade",
          "onUpdate": "no action"
        }
      },
      "compositePrimaryKeys": {},
      "uniqueConstraints": {
        "admission_meta_inquiry_id_unique": {
          "name": "admission_meta_inquiry_id_unique",
          "nullsNotDistinct": false,
          "columns": [
            "inquiry_id"
          ]
        },
        "admission_meta_entry_number_unique": {
          "name": "admission_meta_entry_number_unique",
          "nullsNotDistinct": false,
          "columns": [
            "entry_number"
          ]
        },
        "admission_meta_admission_number_unique": {
          "name": "admission_meta_admission_number_unique",
          "nullsNotDistinct": false,
          "columns": [
            "admission_number"
          ]
        },
        "admission_meta_scholar_number_unique": {
          "name": "admission_meta_scholar_number_unique",
          "nullsNotDistinct": false,
          "columns": [
            "scholar_number"
          ]
        }
      },
      "policies": {},
      "checkConstraints": {},
      "isRLSEnabled": false
    },
    "public.declarations": {
      "name": "declarations",
      "schema": "",
      "columns": {
        "id": {
          "name": "id",
          "type": "uuid",
          "primaryKey": true,
          "notNull": true,
          "default": "gen_random_uuid()"
        },
        "admission_id": {
          "name": "admission_id",
          "type": "uuid",
          "primaryKey": false,
          "notNull": true
        },
        "declaration_accepted": {
          "name": "declaration_accepted",
          "type": "boolean",
          "primaryKey": false,
          "notNull": true,
          "default": false
        },
        "guardian_name": {
          "name": "guardian_name",
          "type": "text",
          "primaryKey": false,
          "notNull": true
        },
        "signature_file": {
          "name": "signature_file",
          "type": "text",
          "primaryKey": false,
          "notNull": false
        },
        "declaration_date": {
          "name": "declaration_date",
          "type": "timestamp",
          "primaryKey": false,
          "notNull": true,
          "default": "now()"
        }
      },
      "indexes": {},
      "foreignKeys": {
        "declarations_admission_id_admission_meta_id_fk": {
          "name": "declarations_admission_id_admission_meta_id_fk",
          "tableFrom": "declarations",
          "tableTo": "admission_meta",
          "columnsFrom": [
            "admission_id"
          ],
          "columnsTo": [
            "id"
          ],
          "onDelete": "cascade",
          "onUpdate": "no action"
        }
      },
      "compositePrimaryKeys": {},
      "uniqueConstraints": {
        "declarations_admission_id_unique": {
          "name": "declarations_admission_id_unique",
          "nullsNotDistinct": false,
          "columns": [
            "admission_id"
          ]
        }
      },
      "policies": {},
      "checkConstraints": {},
      "isRLSEnabled": false
    },
    "public.document_checklists": {
      "name": "document_checklists",
      "schema": "",
      "columns": {
        "id": {
          "name": "id",
          "type": "uuid",
          "primaryKey": true,
          "notNull": true,
          "default": "gen_random_uuid()"
        },
        "admission_id": {
          "name": "admission_id",
          "type": "uuid",
          "primaryKey": false,
          "notNull": true
        },
        "birth_certificate": {
          "name": "birth_certificate",
          "type": "document_status",
          "typeSchema": "public",
          "primaryKey": false,
          "notNull": true,
          "default": "'NOT_SUBMITTED'"
        },
        "previous_marksheet": {
          "name": "previous_marksheet",
          "type": "document_status",
          "typeSchema": "public",
          "primaryKey": false,
          "notNull": true,
          "default": "'NOT_SUBMITTED'"
        },
        "student_photos_3": {
          "name": "student_photos_3",
          "type": "document_status",
          "typeSchema": "public",
          "primaryKey": false,
          "notNull": true,
          "default": "'NOT_SUBMITTED'"
        },
        "caste_certificate": {
          "name": "caste_certificate",
          "type": "document_status",
          "typeSchema": "public",
          "primaryKey": false,
          "notNull": true,
          "default": "'NOT_SUBMITTED'"
        },
        "parent_affidavit": {
          "name": "parent_affidavit",
          "type": "document_status",
          "typeSchema": "public",
          "primaryKey": false,
          "notNull": true,
          "default": "'NOT_SUBMITTED'"
        },
        "scholarship_letter": {
          "name": "scholarship_letter",
          "type": "document_status",
          "typeSchema": "public",
          "primaryKey": false,
          "notNull": true,
          "default": "'NOT_SUBMITTED'"
        },
        "transfer_certificate": {
          "name": "transfer_certificate",
          "type": "document_status",
          "typeSchema": "public",
          "primaryKey": false,
          "notNull": true,
          "default": "'NOT_SUBMITTED'"
        },
        "form_received_complete": {
          "name": "form_received_complete",
          "type": "boolean",
          "primaryKey": false,
          "notNull": true,
          "default": false
        },
        "received_by_name": {
          "name": "received_by_name",
          "type": "text",
          "primaryKey": false,
          "notNull": false
        },
        "principal_sign_date": {
          "name": "principal_sign_date",
          "type": "timestamp",
          "primaryKey": false,
          "notNull": false
        },
        "any_other_details": {
          "name": "any_other_details",
          "type": "text",
          "primaryKey": false,
          "notNull": false
        },
        "verified_at": {
          "name": "verified_at",
          "type": "timestamp",
          "primaryKey": false,
          "notNull": false
        }
      },
      "indexes": {},
      "foreignKeys": {
        "document_checklists_admission_id_admission_meta_id_fk": {
          "name": "document_checklists_admission_id_admission_meta_id_fk",
          "tableFrom": "document_checklists",
          "tableTo": "admission_meta",
          "columnsFrom": [
            "admission_id"
          ],
          "columnsTo": [
            "id"
          ],
          "onDelete": "cascade",
          "onUpdate": "no action"
        }
      },
      "compositePrimaryKeys": {},
      "uniqueConstraints": {
        "document_checklists_admission_id_unique": {
          "name": "document_checklists_admission_id_unique",
          "nullsNotDistinct": false,
          "columns": [
            "admission_id"
          ]
        }
      },
      "policies": {},
      "checkConstraints": {},
      "isRLSEnabled": false
    },
    "public.entrance_tests": {
      "name": "entrance_tests",
      "schema": "",
      "columns": {
        "id": {
          "name": "id",
          "type": "uuid",
          "primaryKey": true,
          "notNull": true,
          "default": "gen_random_uuid()"
        },
        "admission_id": {
          "name": "admission_id",
          "type": "uuid",
          "primaryKey": false,
          "notNull": true
        },
        "test_date": {
          "name": "test_date",
          "type": "text",
          "primaryKey": false,
          "notNull": false
        },
        "test_time": {
          "name": "test_time",
          "type": "text",
          "primaryKey": false,
          "notNull": false
        },
        "location": {
          "name": "location",
          "type": "text",
          "primaryKey": false,
          "notNull": false
        },
        "teacher_name": {
          "name": "teacher_name",
          "type": "text",
          "primaryKey": false,
          "notNull": false
        },
        "contact_number": {
          "name": "contact_number",
          "type": "text",
          "primaryKey": false,
          "notNull": false
        },
        "status": {
          "name": "status",
          "type": "test_status",
          "typeSchema": "public",
          "primaryKey": false,
          "notNull": true,
          "default": "'NOT_SCHEDULED'"
        },
        "result_date": {
          "name": "result_date",
          "type": "timestamp",
          "primaryKey": false,
          "notNull": false
        },
        "remarks": {
          "name": "remarks",
          "type": "text",
          "primaryKey": false,
          "notNull": false
        },
        "created_at": {
          "name": "created_at",
          "type": "timestamp",
          "primaryKey": false,
          "notNull": true,
          "default": "now()"
        },
        "updated_at": {
          "name": "updated_at",
          "type": "timestamp",
          "primaryKey": false,
          "notNull": true,
          "default": "now()"
        }
      },
      "indexes": {},
      "foreignKeys": {
        "entrance_tests_admission_id_admission_meta_id_fk": {
          "name": "entrance_tests_admission_id_admission_meta_id_fk",
          "tableFrom": "entrance_tests",
          "tableTo": "admission_meta",
          "columnsFrom": [
            "admission_id"
          ],
          "columnsTo": [
            "id"
          ],
          "onDelete": "cascade",
          "onUpdate": "no action"
        }
      },
      "compositePrimaryKeys": {},
      "uniqueConstraints": {
        "entrance_tests_admission_id_unique": {
          "name": "entrance_tests_admission_id_unique",
          "nullsNotDistinct": false,
          "columns": [
            "admission_id"
          ]
        }
      },
      "policies": {},
      "checkConstraints": {},
      "isRLSEnabled": false
    },
    "public.inquiries": {
      "name": "inquiries",
      "schema": "",
      "columns": {
        "id": {
          "name": "id",
          "type": "uuid",
          "primaryKey": true,
          "notNull": true,
          "default": "gen_random_uuid()"
        },
        "student_name": {
          "name": "student_name",
          "type": "text",
          "primaryKey": false,
          "notNull": true
        },
        "parent_name": {
          "name": "parent_name",
          "type": "text",
          "primaryKey": false,
          "notNull": true
        },
        "email": {
          "name": "email",
          "type": "text",
          "primaryKey": false,
          "notNull": true
        },
        "phone": {
          "name": "phone",
          "type": "text",
          "primaryKey": false,
          "notNull": true
        },
        "applied_class": {
          "name": "applied_class",
          "type": "text",
          "primaryKey": false,
          "notNull": true
        },
        "academic_year": {
          "name": "academic_year",
          "type": "text",
          "primaryKey": false,
          "notNull": true
        },
        "status": {
          "name": "status",
          "type": "inquiry_status",
          "typeSchema": "public",
          "primaryKey": false,
          "notNull": true,
          "default": "'PENDING'"
        },
        "entry_number": {
          "name": "entry_number",
          "type": "text",
          "primaryKey": false,
          "notNull": false
        },
        "created_at": {
          "name": "created_at",
          "type": "timestamp",
          "primaryKey": false,
          "notNull": true,
          "default": "now()"
        },
        "updated_at": {
          "name": "updated_at",
          "type": "timestamp",
          "primaryKey": false,
          "notNull": true,
          "default": "now()"
        }
      },
      "indexes": {},
      "foreignKeys": {},
      "compositePrimaryKeys": {},
      "uniqueConstraints": {
        "inquiries_entry_number_unique": {
          "name": "inquiries_entry_number_unique",
          "nullsNotDistinct": false,
          "columns": [
            "entry_number"
          ]
        }
      },
      "policies": {},
      "checkConstraints": {},
      "isRLSEnabled": false
    },
    "public.parent_guardian_details": {
      "name": "parent_guardian_details",
      "schema": "",
      "columns": {
        "id": {
          "name": "id",
          "type": "uuid",
          "primaryKey": true,
          "notNull": true,
          "default": "gen_random_uuid()"
        },
        "admission_id": {
          "name": "admission_id",
          "type": "uuid",
          "primaryKey": false,
          "notNull": true
        },
        "person_type": {
          "name": "person_type",
          "type": "text",
          "primaryKey": false,
          "notNull": true
        },
        "is_single_parent": {
          "name": "is_single_parent",
          "type": "boolean",
          "primaryKey": false,
          "notNull": true,
          "default": false
        },
        "legal_guardian_type": {
          "name": "legal_guardian_type",
          "type": "text",
          "primaryKey": false,
          "notNull": false
        },
        "name": {
          "name": "name",
          "type": "text",
          "primaryKey": false,
          "notNull": true
        },
        "mobile_number": {
          "name": "mobile_number",
          "type": "text",
          "primaryKey": false,
          "notNull": true
        },
        "occupation": {
          "name": "occupation",
          "type": "text",
          "primaryKey": false,
          "notNull": false
        },
        "qualification": {
          "name": "qualification",
          "type": "text",
          "primaryKey": false,
          "notNull": false
        },
        "aadhaar_number": {
          "name": "aadhaar_number",
          "type": "text",
          "primaryKey": false,
          "notNull": false
        },
        "samagra_number": {
          "name": "samagra_number",
          "type": "text",
          "primaryKey": false,
          "notNull": false
        },
        "relation": {
          "name": "relation",
          "type": "text",
          "primaryKey": false,
          "notNull": false
        },
        "office_shop_name": {
          "name": "office_shop_name",
          "type": "text",
          "primaryKey": false,
          "notNull": false
        },
        "job_details": {
          "name": "job_details",
          "type": "text",
          "primaryKey": false,
          "notNull": false
        },
        "photo": {
          "name": "photo",
          "type": "text",
          "primaryKey": false,
          "notNull": false
        }
      },
      "indexes": {},
      "foreignKeys": {
        "parent_guardian_details_admission_id_admission_meta_id_fk": {
          "name": "parent_guardian_details_admission_id_admission_meta_id_fk",
          "tableFrom": "parent_guardian_details",
          "tableTo": "admission_meta",
          "columnsFrom": [
            "admission_id"
          ],
          "columnsTo": [
            "id"
          ],
          "onDelete": "cascade",
          "onUpdate": "no action"
        }
      },
      "compositePrimaryKeys": {},
      "uniqueConstraints": {},
      "policies": {},
      "checkConstraints": {},
      "isRLSEnabled": false
    },
    "public.previous_academic": {
      "name": "previous_academic",
      "schema": "",
      "columns": {
        "id": {
          "name": "id",
          "type": "uuid",
          "primaryKey": true,
          "notNull": true,
          "default": "gen_random_uuid()"
        },
        "admission_id": {
          "name": "admission_id",
          "type": "uuid",
          "primaryKey": false,
          "notNull": true
        },
        "school_name": {
          "name": "school_name",
          "type": "text",
          "primaryKey": false,
          "notNull": true
        },
        "school_type": {
          "name": "school_type",
          "type": "text",
          "primaryKey": false,
          "notNull": true
        },
        "apaar_id": {
          "name": "apaar_id",
          "type": "text",
          "primaryKey": false,
          "notNull": false
        },
        "pen_number": {
          "name": "pen_number",
          "type": "text",
          "primaryKey": false,
          "notNull": false
        },
        "class_last_attended": {
          "name": "class_last_attended",
          "type": "text",
          "primaryKey": false,
          "notNull": false
        },
        "session_year": {
          "name": "session_year",
          "type": "text",
          "primaryKey": false,
          "notNull": false
        },
        "marks_obtained": {
          "name": "marks_obtained",
          "type": "double precision",
          "primaryKey": false,
          "notNull": false
        },
        "total_marks": {
          "name": "total_marks",
          "type": "double precision",
          "primaryKey": false,
          "notNull": false
        },
        "percentage": {
          "name": "percentage",
          "type": "double precision",
          "primaryKey": false,
          "notNull": false
        },
        "pass_fail": {
          "name": "pass_fail",
          "type": "text",
          "primaryKey": false,
          "notNull": false
        }
      },
      "indexes": {},
      "foreignKeys": {
        "previous_academic_admission_id_admission_meta_id_fk": {
          "name": "previous_academic_admission_id_admission_meta_id_fk",
          "tableFrom": "previous_academic",
          "tableTo": "admission_meta",
          "columnsFrom": [
            "admission_id"
          ],
          "columnsTo": [
            "id"
          ],
          "onDelete": "cascade",
          "onUpdate": "no action"
        }
      },
      "compositePrimaryKeys": {},
      "uniqueConstraints": {
        "previous_academic_admission_id_unique": {
          "name": "previous_academic_admission_id_unique",
          "nullsNotDistinct": false,
          "columns": [
            "admission_id"
          ]
        }
      },
      "policies": {},
      "checkConstraints": {},
      "isRLSEnabled": false
    },
    "public.sibling_details": {
      "name": "sibling_details",
      "schema": "",
      "columns": {
        "id": {
          "name": "id",
          "type": "uuid",
          "primaryKey": true,
          "notNull": true,
          "default": "gen_random_uuid()"
        },
        "admission_id": {
          "name": "admission_id",
          "type": "uuid",
          "primaryKey": false,
          "notNull": true
        },
        "sibling_number": {
          "name": "sibling_number",
          "type": "integer",
          "primaryKey": false,
          "notNull": true
        },
        "name": {
          "name": "name",
          "type": "text",
          "primaryKey": false,
          "notNull": true
        },
        "age": {
          "name": "age",
          "type": "integer",
          "primaryKey": false,
          "notNull": false
        },
        "gender": {
          "name": "gender",
          "type": "gender",
          "typeSchema": "public",
          "primaryKey": false,
          "notNull": false
        },
        "class_current": {
          "name": "class_current",
          "type": "text",
          "primaryKey": false,
          "notNull": false
        },
        "school_name": {
          "name": "school_name",
          "type": "text",
          "primaryKey": false,
          "notNull": false
        }
      },
      "indexes": {},
      "foreignKeys": {
        "sibling_details_admission_id_admission_meta_id_fk": {
          "name": "sibling_details_admission_id_admission_meta_id_fk",
          "tableFrom": "sibling_details",
          "tableTo": "admission_meta",
          "columnsFrom": [
            "admission_id"
          ],
          "columnsTo": [
            "id"
          ],
          "onDelete": "cascade",
          "onUpdate": "no action"
        }
      },
      "compositePrimaryKeys": {},
      "uniqueConstraints": {},
      "policies": {},
      "checkConstraints": {},
      "isRLSEnabled": false
    },
    "public.student_address": {
      "name": "student_address",
      "schema": "",
      "columns": {
        "id": {
          "name": "id",
          "type": "uuid",
          "primaryKey": true,
          "notNull": true,
          "default": "gen_random_uuid()"
        },
        "admission_id": {
          "name": "admission_id",
          "type": "uuid",
          "primaryKey": false,
          "notNull": true
        },
        "house_no": {
          "name": "house_no",
          "type": "text",
          "primaryKey": false,
          "notNull": true
        },
        "ward_no": {
          "name": "ward_no",
          "type": "text",
          "primaryKey": false,
          "notNull": false
        },
        "street": {
          "name": "street",
          "type": "text",
          "primaryKey": false,
          "notNull": true
        },
        "village": {
          "name": "village",
          "type": "text",
          "primaryKey": false,
          "notNull": true
        },
        "tehsil": {
          "name": "tehsil",
          "type": "text",
          "primaryKey": false,
          "notNull": false
        },
        "district": {
          "name": "district",
          "type": "text",
          "primaryKey": false,
          "notNull": false
        },
        "state": {
          "name": "state",
          "type": "text",
          "primaryKey": false,
          "notNull": false
        },
        "pin_code": {
          "name": "pin_code",
          "type": "text",
          "primaryKey": false,
          "notNull": false
        }
      },
      "indexes": {},
      "foreignKeys": {
        "student_address_admission_id_admission_meta_id_fk": {
          "name": "student_address_admission_id_admission_meta_id_fk",
          "tableFrom": "student_address",
          "tableTo": "admission_meta",
          "columnsFrom": [
            "admission_id"
          ],
          "columnsTo": [
            "id"
          ],
          "onDelete": "cascade",
          "onUpdate": "no action"
        }
      },
      "compositePrimaryKeys": {},
      "uniqueConstraints": {
        "student_address_admission_id_unique": {
          "name": "student_address_admission_id_unique",
          "nullsNotDistinct": false,
          "columns": [
            "admission_id"
          ]
        }
      },
      "policies": {},
      "checkConstraints": {},
      "isRLSEnabled": false
    },
    "public.student_bank_details": {
      "name": "student_bank_details",
      "schema": "",
      "columns": {
        "id": {
          "name": "id",
          "type": "uuid",
          "primaryKey": true,
          "notNull": true,
          "default": "gen_random_uuid()"
        },
        "admission_id": {
          "name": "admission_id",
          "type": "uuid",
          "primaryKey": false,
          "notNull": true
        },
        "bank_name": {
          "name": "bank_name",
          "type": "text",
          "primaryKey": false,
          "notNull": false
        },
        "account_holder_name": {
          "name": "account_holder_name",
          "type": "text",
          "primaryKey": false,
          "notNull": false
        },
        "account_number": {
          "name": "account_number",
          "type": "text",
          "primaryKey": false,
          "notNull": false
        },
        "ifsc_code": {
          "name": "ifsc_code",
          "type": "text",
          "primaryKey": false,
          "notNull": false
        },
        "note": {
          "name": "note",
          "type": "text",
          "primaryKey": false,
          "notNull": false
        }
      },
      "indexes": {},
      "foreignKeys": {
        "student_bank_details_admission_id_admission_meta_id_fk": {
          "name": "student_bank_details_admission_id_admission_meta_id_fk",
          "tableFrom": "student_bank_details",
          "tableTo": "admission_meta",
          "columnsFrom": [
            "admission_id"
          ],
          "columnsTo": [
            "id"
          ],
          "onDelete": "cascade",
          "onUpdate": "no action"
        }
      },
      "compositePrimaryKeys": {},
      "uniqueConstraints": {
        "student_bank_details_admission_id_unique": {
          "name": "student_bank_details_admission_id_unique",
          "nullsNotDistinct": false,
          "columns": [
            "admission_id"
          ]
        }
      },
      "policies": {},
      "checkConstraints": {},
      "isRLSEnabled": false
    },
    "public.student_bio": {
      "name": "student_bio",
      "schema": "",
      "columns": {
        "id": {
          "name": "id",
          "type": "uuid",
          "primaryKey": true,
          "notNull": true,
          "default": "gen_random_uuid()"
        },
        "admission_id": {
          "name": "admission_id",
          "type": "uuid",
          "primaryKey": false,
          "notNull": true
        },
        "first_name": {
          "name": "first_name",
          "type": "text",
          "primaryKey": false,
          "notNull": true
        },
        "middle_name": {
          "name": "middle_name",
          "type": "text",
          "primaryKey": false,
          "notNull": false
        },
        "last_name": {
          "name": "last_name",
          "type": "text",
          "primaryKey": false,
          "notNull": true
        },
        "gender": {
          "name": "gender",
          "type": "gender",
          "typeSchema": "public",
          "primaryKey": false,
          "notNull": true
        },
        "dob": {
          "name": "dob",
          "type": "timestamp",
          "primaryKey": false,
          "notNull": true
        },
        "age": {
          "name": "age",
          "type": "integer",
          "primaryKey": false,
          "notNull": true
        },
        "religion": {
          "name": "religion",
          "type": "text",
          "primaryKey": false,
          "notNull": false
        },
        "caste": {
          "name": "caste",
          "type": "caste",
          "typeSchema": "public",
          "primaryKey": false,
          "notNull": true
        },
        "family_id": {
          "name": "family_id",
          "type": "text",
          "primaryKey": false,
          "notNull": false
        },
        "blood_group": {
          "name": "blood_group",
          "type": "text",
          "primaryKey": false,
          "notNull": false
        },
        "height_cm": {
          "name": "height_cm",
          "type": "double precision",
          "primaryKey": false,
          "notNull": false
        },
        "weight_kg": {
          "name": "weight_kg",
          "type": "double precision",
          "primaryKey": false,
          "notNull": false
        },
        "aadhaar_number": {
          "name": "aadhaar_number",
          "type": "text",
          "primaryKey": false,
          "notNull": false
        },
        "samagra_id": {
          "name": "samagra_id",
          "type": "text",
          "primaryKey": false,
          "notNull": false
        },
        "cwsn": {
          "name": "cwsn",
          "type": "boolean",
          "primaryKey": false,
          "notNull": true,
          "default": false
        },
        "cwsn_problem_desc": {
          "name": "cwsn_problem_desc",
          "type": "text",
          "primaryKey": false,
          "notNull": false
        },
        "student_photo": {
          "name": "student_photo",
          "type": "text",
          "primaryKey": false,
          "notNull": false
        }
      },
      "indexes": {},
      "foreignKeys": {
        "student_bio_admission_id_admission_meta_id_fk": {
          "name": "student_bio_admission_id_admission_meta_id_fk",
          "tableFrom": "student_bio",
          "tableTo": "admission_meta",
          "columnsFrom": [
            "admission_id"
          ],
          "columnsTo": [
            "id"
          ],
          "onDelete": "cascade",
          "onUpdate": "no action"
        }
      },
      "compositePrimaryKeys": {},
      "uniqueConstraints": {
        "student_bio_admission_id_unique": {
          "name": "student_bio_admission_id_unique",
          "nullsNotDistinct": false,
          "columns": [
            "admission_id"
          ]
        }
      },
      "policies": {},
      "checkConstraints": {},
      "isRLSEnabled": false
    },
    "public.student_documents": {
      "name": "student_documents",
      "schema": "",
      "columns": {
        "id": {
          "name": "id",
          "type": "uuid",
          "primaryKey": true,
          "notNull": true,
          "default": "gen_random_uuid()"
        },
        "admission_id": {
          "name": "admission_id",
          "type": "uuid",
          "primaryKey": false,
          "notNull": true
        },
        "birth_certificate": {
          "name": "birth_certificate",
          "type": "text",
          "primaryKey": false,
          "notNull": false
        },
        "student_photo": {
          "name": "student_photo",
          "type": "text",
          "primaryKey": false,
          "notNull": false
        },
        "marksheet": {
          "name": "marksheet",
          "type": "text",
          "primaryKey": false,
          "notNull": false
        },
        "caste_certificate": {
          "name": "caste_certificate",
          "type": "text",
          "primaryKey": false,
          "notNull": false
        },
        "affidavit": {
          "name": "affidavit",
          "type": "text",
          "primaryKey": false,
          "notNull": false
        },
        "transfer_certificate": {
          "name": "transfer_certificate",
          "type": "text",
          "primaryKey": false,
          "notNull": false
        },
        "scholarship_slip": {
          "name": "scholarship_slip",
          "type": "text",
          "primaryKey": false,
          "notNull": false
        },
        "created_at": {
          "name": "created_at",
          "type": "timestamp",
          "primaryKey": false,
          "notNull": true,
          "default": "now()"
        },
        "updated_at": {
          "name": "updated_at",
          "type": "timestamp",
          "primaryKey": false,
          "notNull": true,
          "default": "now()"
        }
      },
      "indexes": {},
      "foreignKeys": {
        "student_documents_admission_id_admission_meta_id_fk": {
          "name": "student_documents_admission_id_admission_meta_id_fk",
          "tableFrom": "student_documents",
          "tableTo": "admission_meta",
          "columnsFrom": [
            "admission_id"
          ],
          "columnsTo": [
            "id"
          ],
          "onDelete": "cascade",
          "onUpdate": "no action"
        }
      },
      "compositePrimaryKeys": {},
      "uniqueConstraints": {
        "student_documents_admission_id_unique": {
          "name": "student_documents_admission_id_unique",
          "nullsNotDistinct": false,
          "columns": [
            "admission_id"
          ]
        }
      },
      "policies": {},
      "checkConstraints": {},
      "isRLSEnabled": false
    },
    "public.student_profiles": {
      "name": "student_profiles",
      "schema": "",
      "columns": {
        "id": {
          "name": "id",
          "type": "uuid",
          "primaryKey": true,
          "notNull": true,
          "default": "gen_random_uuid()"
        },
        "user_id": {
          "name": "user_id",
          "type": "uuid",
          "primaryKey": false,
          "notNull": true
        },
        "admission_meta_id": {
          "name": "admission_meta_id",
          "type": "uuid",
          "primaryKey": false,
          "notNull": false
        },
        "admission_step": {
          "name": "admission_step",
          "type": "integer",
          "primaryKey": false,
          "notNull": true,
          "default": 1
        },
        "is_fully_admitted": {
          "name": "is_fully_admitted",
          "type": "boolean",
          "primaryKey": false,
          "notNull": true,
          "default": false
        }
      },
      "indexes": {},
      "foreignKeys": {
        "student_profiles_user_id_users_id_fk": {
          "name": "student_profiles_user_id_users_id_fk",
          "tableFrom": "student_profiles",
          "tableTo": "users",
          "columnsFrom": [
            "user_id"
          ],
          "columnsTo": [
            "id"
          ],
          "onDelete": "cascade",
          "onUpdate": "no action"
        },
        "student_profiles_admission_meta_id_admission_meta_id_fk": {
          "name": "student_profiles_admission_meta_id_admission_meta_id_fk",
          "tableFrom": "student_profiles",
          "tableTo": "admission_meta",
          "columnsFrom": [
            "admission_meta_id"
          ],
          "columnsTo": [
            "id"
          ],
          "onDelete": "no action",
          "onUpdate": "no action"
        }
      },
      "compositePrimaryKeys": {},
      "uniqueConstraints": {
        "student_profiles_user_id_unique": {
          "name": "student_profiles_user_id_unique",
          "nullsNotDistinct": false,
          "columns": [
            "user_id"
          ]
        }
      },
      "policies": {},
      "checkConstraints": {},
      "isRLSEnabled": false
    },
    "public.users": {
      "name": "users",
      "schema": "",
      "columns": {
        "id": {
          "name": "id",
          "type": "uuid",
          "primaryKey": true,
          "notNull": true,
          "default": "gen_random_uuid()"
        },
        "email": {
          "name": "email",
          "type": "text",
          "primaryKey": false,
          "notNull": true
        },
        "password": {
          "name": "password",
          "type": "text",
          "primaryKey": false,
          "notNull": true
        },
        "role": {
          "name": "role",
          "type": "role",
          "typeSchema": "public",
          "primaryKey": false,
          "notNull": true,
          "default": "'OFFICE'"
        },
        "phone": {
          "name": "phone",
          "type": "text",
          "primaryKey": false,
          "notNull": false
        },
        "created_at": {
          "name": "created_at",
          "type": "timestamp",
          "primaryKey": false,
          "notNull": true,
          "default": "now()"
        },
        "updated_at": {
          "name": "updated_at",
          "type": "timestamp",
          "primaryKey": false,
          "notNull": true,
          "default": "now()"
        }
      },
      "indexes": {},
      "foreignKeys": {},
      "compositePrimaryKeys": {},
      "uniqueConstraints": {
        "users_email_unique": {
          "name": "users_email_unique",
          "nullsNotDistinct": false,
          "columns": [
            "email"
          ]
        }
      },
      "policies": {},
      "checkConstraints": {},
      "isRLSEnabled": false
    }
  },
  "enums": {
    "public.admission_type": {
      "name": "admission_type",
      "schema": "public",
      "values": [
        "NEW",
        "RE_ADMISSION"
      ]
    },
    "public.caste": {
      "name": "caste",
      "schema": "public",
      "values": [
        "GEN",
        "OBC",
        "ST",
        "SC"
      ]
    },
    "public.document_status": {
      "name": "document_status",
      "schema": "public",
      "values": [
        "SUBMITTED",
        "NOT_SUBMITTED"
      ]
    },
    "public.gender": {
      "name": "gender",
      "schema": "public",
      "values": [
        "M",
        "F",
        "O"
      ]
    },
    "public.inquiry_status": {
      "name": "inquiry_status",
      "schema": "public",
      "values": [
        "PENDING",
        "SHORTLISTED",
        "REJECTED"
      ]
    },
    "public.role": {
      "name": "role",
      "schema": "public",
      "values": [
        "OFFICE",
        "STUDENT_PARENT"
      ]
    },
    "public.test_status": {
      "name": "test_status",
      "schema": "public",
      "values": [
        "NOT_SCHEDULED",
        "PENDING",
        "PASS",
        "FAIL"
      ]
    }
  },
  "schemas": {},
  "sequences": {},
  "roles": {},
  "policies": {},
  "views": {},
  "_meta": {
    "columns": {},
    "schemas": {},
    "tables": {}
  }
}